vtt_to_srt/__init__.py
vtt_to_srt/vtt_to_srt.py
vtt_to_srt2-0.2.0.4.dist-info/LICENSE
vtt_to_srt2-0.2.0.4.dist-info/METADATA
vtt_to_srt2-0.2.0.4.dist-info/WHEEL
vtt_to_srt2-0.2.0.4.dist-info/entry_points.txt
vtt_to_srt2-0.2.0.4.dist-info/top_level.txt
vtt_to_srt2-0.2.0.4.dist-info/RECORD
