Metadata-Version: 2.1
Name: vtt_to_srt2
Version: 0.2.0.4
Summary: vtt to srt subtitles converter package
Home-page: https://github.com/jsonzilla/vtt_to_srt2
Author: Jeison Cardoso
Author-email: j@jsonzilla.com
Maintainer: Jeison Cardoso
Classifier: Programming Language :: Python :: 2.7
Classifier: Operating System :: OS Independent
License-File: LICENSE
